MonsterLab/__init__.py
MonsterLab/monster_lab.py
MonsterLab/monsters.py
monsterlab-2.1.0.dist-info/METADATA
monsterlab-2.1.0.dist-info/WHEEL
monsterlab-2.1.0.dist-info/top_level.txt
monsterlab-2.1.0.dist-info/RECORD
