Metadata-Version: 2.4
Name: monsterlab
Version: 2.1.0
Summary: Monster Generator
Home-page: https://github.com/BrokenShell/MonsterLab
Author: Robert Sharp
Author-email: webmaster@sharpdesigndigital.com
License: Free for non-commercial use
Keywords: MonsterLab
Platform: Darwin
Platform: Linux
Classifier: Development Status :: 5 - Production/Stable
Classifier: Programming Language :: Python :: 3.9
Requires-Python: >=3.7
Requires-Dist: pytz
Dynamic: author
Dynamic: author-email
Dynamic: classifier
Dynamic: description
Dynamic: description-content-type
Dynamic: home-page
Dynamic: keywords
Dynamic: license
Dynamic: platform
Dynamic: requires-dist
Dynamic: requires-python
Dynamic: summary
